monday/__init__.py
monday/__version__.py
monday/client.py
monday/exceptions.py
monday/query_joins.py
monday/utils.py
monday/graphqlclient/client.py
monday/resources/__init__.py
monday/resources/base.py
monday/resources/boards.py
monday/resources/columns.py
monday/resources/complexity.py
monday/resources/custom.py
monday/resources/groups.py
monday/resources/items.py
monday/resources/me.py
monday/resources/notification.py
monday/resources/tags.py
monday/resources/types.py
monday/resources/updates.py
monday/resources/users.py
monday/resources/workspaces.py
mgmonday-2.0.2.dist-info/LICENSE
mgmonday-2.0.2.dist-info/METADATA
mgmonday-2.0.2.dist-info/WHEEL
mgmonday-2.0.2.dist-info/top_level.txt
mgmonday-2.0.2.dist-info/RECORD
