Metadata-Version: 2.1
Name: mgmonday
Version: 2.0.2
Summary: A (fork of a) Python client library for Monday.com
Home-page: https://github.com/mgmonteleone/monday
Author: Matthew Monteleone et al.
Author-email: mgm@mongodb.com, chdastolfo@gmail.com, lemi@prodperfect.com, pevner@prodperfect.com
License: BSD
Classifier: Programming Language :: Python :: 3
Classifier: Programming Language :: Python :: 3.9
Classifier: Programming Language :: Python :: 3.10
Classifier: Programming Language :: Python :: 3.11
Classifier: Programming Language :: Python :: 3.12
Classifier: Operating System :: OS Independent
Requires-Python: >=3.9
License-File: LICENSE
